FullFileHandler/Exceptions.py
FullFileHandler/Modes.py
FullFileHandler/PDFFileHandler.py
FullFileHandler/TextFileHandler.py
FullFileHandler/__init__.py
FullFileHandler/test.py
full_file_handler-0.0.4.dist-info/LICENSE
full_file_handler-0.0.4.dist-info/METADATA
full_file_handler-0.0.4.dist-info/WHEEL
full_file_handler-0.0.4.dist-info/top_level.txt
full_file_handler-0.0.4.dist-info/RECORD
