Metadata-Version: 2.1
Name: full-file-handler
Version: 0.0.4
Summary: File Handler
Home-page: UNKNOWN
Author: Jenil Chudgar
Author-email: jenilchudgarfamily@gmail.com
License: UNKNOWN
Keywords: file,file handling,file io,easy file
Platform: UNKNOWN
Classifier: Development Status :: 1 - Planning
Classifier: Intended Audience :: Developers
Classifier: Programming Language :: Python :: 3
Classifier: Operating System :: Unix
Classifier: Operating System :: MacOS :: MacOS X
Classifier: Operating System :: Microsoft :: Windows
License-File: LICENSE
Requires-Dist: PyPDF2
